bakaano/__init__.py
bakaano/alpha_earth.py
bakaano/dem.py
bakaano/meteo.py
bakaano/ndvi.py
bakaano/pet.py
bakaano/plot_runoff.py
bakaano/router.py
bakaano/runner.py
bakaano/soil.py
bakaano/streamflow_simulator.py
bakaano/streamflow_trainer.py
bakaano/tree_cover.py
bakaano/utils.py
bakaano/veget.py
bakaano_hydro-1.3.1.dist-info/licenses/LICENSE
bakaano_hydro-1.3.1.dist-info/METADATA
bakaano_hydro-1.3.1.dist-info/WHEEL
bakaano_hydro-1.3.1.dist-info/top_level.txt
bakaano_hydro-1.3.1.dist-info/RECORD
