Metadata-Version: 2.4
Name: bakaano-hydro
Version: 1.3.1
Summary: Distributed hydrology-guided neural network for streamflow prediction
Home-page: https://github.com/confidence-duku/bakaano-hydro
Author: Confidence Duku
Author-email: confidence.duku@gmail.com
License: Apache 2.0
Project-URL: Source, https://github.com/confidence-duku/bakaano-hydro
Project-URL: Bug Tracker, https://github.com/confidence-duku/bakaano-hydro/issues
Project-URL: Documentation, https://github.com/confidence-duku/bakaano-hydro#readme
Keywords: hydrology earth system flood forecasting deep learning streamflow prediction climate risk
Classifier: Development Status :: 4 - Beta
Classifier: Intended Audience :: Science/Research
Classifier: Topic :: Scientific/Engineering :: Hydrology
Classifier: License :: OSI Approved :: Apache Software License
Classifier: Programming Language :: Python :: 3.10
Classifier: Operating System :: OS Independent
Requires-Python: >=3.10
License-File: LICENSE
Requires-Dist: dask==2024.11.2
Requires-Dist: earthengine-api==1.4.3
Requires-Dist: fiona==1.10.1
Requires-Dist: future==1.0.0
Requires-Dist: geemap==0.35.1
Requires-Dist: geopandas==1.0.1
Requires-Dist: hydroeval==0.1.0
Requires-Dist: isimip-client==1.0.1
Requires-Dist: keras==3.6.0
Requires-Dist: localtileserver==0.10.6
Requires-Dist: leafmap==0.43.6
Requires-Dist: keras-tcn==3.5.6
Requires-Dist: matplotlib==3.9.2
Requires-Dist: netCDF4==1.7.2
Requires-Dist: numpy==1.26.4
Requires-Dist: slicer==0.0.7
Requires-Dist: pandas==2.2.3
Requires-Dist: pysheds==0.3.3
Requires-Dist: rasterio==1.4.2
Requires-Dist: requests==2.32.3
Requires-Dist: rioxarray
Requires-Dist: scipy==1.14.1
Requires-Dist: shapely==2.0.6
Requires-Dist: tensorflow==2.18.0
Requires-Dist: tensorflow_probability==0.25.0
Requires-Dist: tf_keras==2.18.0
Requires-Dist: xarray==2024.10.0
Requires-Dist: tqdm==4.67.1
Requires-Dist: scikit-learn==1.5.2
Provides-Extra: gpu
Requires-Dist: nvidia-cublas-cu12==12.5.3.2; extra == "gpu"
Requires-Dist: nvidia-cuda-cupti-cu12==12.5.82; extra == "gpu"
Requires-Dist: nvidia-cuda-nvcc-cu12==12.5.82; extra == "gpu"
Requires-Dist: nvidia-cuda-nvrtc-cu12==12.5.82; extra == "gpu"
Requires-Dist: nvidia-cuda-runtime-cu12==12.5.82; extra == "gpu"
Requires-Dist: nvidia-cudnn-cu12==9.3.0.75; extra == "gpu"
Requires-Dist: nvidia-cufft-cu12==11.2.3.61; extra == "gpu"
Requires-Dist: nvidia-curand-cu12==10.3.6.82; extra == "gpu"
Requires-Dist: nvidia-cusolver-cu12==11.6.3.83; extra == "gpu"
Requires-Dist: nvidia-cusparse-cu12==12.5.1.3; extra == "gpu"
Requires-Dist: nvidia-nvjitlink-cu12==12.5.82; extra == "gpu"
Dynamic: author
Dynamic: author-email
Dynamic: classifier
Dynamic: description
Dynamic: description-content-type
Dynamic: home-page
Dynamic: keywords
Dynamic: license
Dynamic: license-file
Dynamic: project-url
Dynamic: provides-extra
Dynamic: requires-dist
Dynamic: requires-python
Dynamic: summary
